[
  {
    "numero_procedimento": "N/A",
    "entidade": "Anúncio de procedimento  n.º 16511/2026  -  Diário da República n.º 123/2026, Série II de 2026-06-29",
    "link": "https://diariodarepublica.pt/dr/detalhe/anuncio-procedimento/16511-2026-1139897677"
  },
  {
    "numero_procedimento": "N/A",
    "entidade": "Anúncio de procedimento  n.º 16513/2026  -  Diário da República n.º 123/2026, Série II de 2026-06-29",
    "link": "https://diariodarepublica.pt/dr/detalhe/anuncio-procedimento/16513-2026-1139897678"
  },
  {
    "numero_procedimento": "N/A",
    "entidade": "Anúncio de procedimento  n.º 16516/2026  -  Diário da República n.º 123/2026, Série II de 2026-06-29",
    "link": "https://diariodarepublica.pt/dr/detalhe/anuncio-procedimento/16516-2026-1139897679"
  },
  {
    "numero_procedimento": "N/A",
    "entidade": "Anúncio de procedimento  n.º 16518/2026  -  Diário da República n.º 123/2026, Série II de 2026-06-29",
    "link": "https://diariodarepublica.pt/dr/detalhe/anuncio-procedimento/16518-2026-1139897696"
  },
  {
    "numero_procedimento": "N/A",
    "entidade": "Anúncio de procedimento  n.º 16510/2026  -  Diário da República n.º 123/2026, Série II de 2026-06-29",
    "link": "https://diariodarepublica.pt/dr/detalhe/anuncio-procedimento/16510-2026-1139905282"
  },
  {
    "numero_procedimento": "N/A",
    "entidade": "Anúncio de procedimento  n.º 16512/2026  -  Diário da República n.º 123/2026, Série II de 2026-06-29",
    "link": "https://diariodarepublica.pt/dr/detalhe/anuncio-procedimento/16512-2026-1139905283"
  },
  {
    "numero_procedimento": "N/A",
    "entidade": "Anúncio de procedimento  n.º 16514/2026  -  Diário da República n.º 123/2026, Série II de 2026-06-29",
    "link": "https://diariodarepublica.pt/dr/detalhe/anuncio-procedimento/16514-2026-1139905284"
  },
  {
    "numero_procedimento": "N/A",
    "entidade": "Anúncio de procedimento  n.º 16515/2026  -  Diário da República n.º 123/2026, Série II de 2026-06-29",
    "link": "https://diariodarepublica.pt/dr/detalhe/anuncio-procedimento/16515-2026-1139905285"
  },
  {
    "numero_procedimento": "N/A",
    "entidade": "Anúncio de procedimento  n.º 16517/2026  -  Diário da República n.º 123/2026, Série II de 2026-06-29",
    "link": "https://diariodarepublica.pt/dr/detalhe/anuncio-procedimento/16517-2026-1139905305"
  },
  {
    "numero_procedimento": "N/A",
    "entidade": "Anúncio de procedimento  n.º 16520/2026  -  Diário da República n.º 123/2026, Série II de 2026-06-29",
    "link": "https://diariodarepublica.pt/dr/detalhe/anuncio-procedimento/16520-2026-1139905306"
  },
  {
    "numero_procedimento": "N/A",
    "entidade": "Anúncio de procedimento  n.º 16521/2026  -  Diário da República n.º 123/2026, Série II de 2026-06-29",
    "link": "https://diariodarepublica.pt/dr/detalhe/anuncio-procedimento/16521-2026-1139905307"
  },
  {
    "numero_procedimento": "N/A",
    "entidade": "Anúncio de procedimento  n.º 16525/2026  -  Diário da República n.º 123/2026, Série II de 2026-06-29",
    "link": "https://diariodarepublica.pt/dr/detalhe/anuncio-procedimento/16525-2026-1139905308"
  },
  {
    "numero_procedimento": "N/A",
    "entidade": "Anúncio de procedimento  n.º 16526/2026  -  Diário da República n.º 123/2026, Série II de 2026-06-29",
    "link": "https://diariodarepublica.pt/dr/detalhe/anuncio-procedimento/16526-2026-1139905309"
  },
  {
    "numero_procedimento": "N/A",
    "entidade": "Anúncio de procedimento  n.º 16528/2026  -  Diário da República n.º 123/2026, Série II de 2026-06-29",
    "link": "https://diariodarepublica.pt/dr/detalhe/anuncio-procedimento/16528-2026-1139905310"
  },
  {
    "numero_procedimento": "N/A",
    "entidade": "Anúncio de procedimento  n.º 16530/2026  -  Diário da República n.º 123/2026, Série II de 2026-06-29",
    "link": "https://diariodarepublica.pt/dr/detalhe/anuncio-procedimento/16530-2026-1139905311"
  },
  {
    "numero_procedimento": "N/A",
    "entidade": "Anúncio de procedimento  n.º 16532/2026  -  Diário da República n.º 123/2026, Série II de 2026-06-29",
    "link": "https://diariodarepublica.pt/dr/detalhe/anuncio-procedimento/16532-2026-1139905312"
  },
  {
    "numero_procedimento": "N/A",
    "entidade": "Anúncio de procedimento  n.º 16534/2026  -  Diário da República n.º 123/2026, Série II de 2026-06-29",
    "link": "https://diariodarepublica.pt/dr/detalhe/anuncio-procedimento/16534-2026-1139905313"
  },
  {
    "numero_procedimento": "N/A",
    "entidade": "Anúncio de procedimento  n.º 16536/2026  -  Diário da República n.º 123/2026, Série II de 2026-06-29",
    "link": "https://diariodarepublica.pt/dr/detalhe/anuncio-procedimento/16536-2026-1139905314"
  },
  {
    "numero_procedimento": "N/A",
    "entidade": "Anúncio de procedimento  n.º 16538/2026  -  Diário da República n.º 123/2026, Série II de 2026-06-29",
    "link": "https://diariodarepublica.pt/dr/detalhe/anuncio-procedimento/16538-2026-1139905315"
  },
  {
    "numero_procedimento": "N/A",
    "entidade": "Anúncio de procedimento  n.º 16540/2026  -  Diário da República n.º 123/2026, Série II de 2026-06-29",
    "link": "https://diariodarepublica.pt/dr/detalhe/anuncio-procedimento/16540-2026-1139905316"
  },
  {
    "numero_procedimento": "N/A",
    "entidade": "Anúncio de procedimento  n.º 16542/2026  -  Diário da República n.º 123/2026, Série II de 2026-06-29",
    "link": "https://diariodarepublica.pt/dr/detalhe/anuncio-procedimento/16542-2026-1139905317"
  },
  {
    "numero_procedimento": "N/A",
    "entidade": "Anúncio de procedimento  n.º 16544/2026  -  Diário da República n.º 123/2026, Série II de 2026-06-29",
    "link": "https://diariodarepublica.pt/dr/detalhe/anuncio-procedimento/16544-2026-1139905318"
  },
  {
    "numero_procedimento": "N/A",
    "entidade": "Anúncio de procedimento  n.º 16546/2026  -  Diário da República n.º 123/2026, Série II de 2026-06-29",
    "link": "https://diariodarepublica.pt/dr/detalhe/anuncio-procedimento/16546-2026-1139905319"
  },
  {
    "numero_procedimento": "N/A",
    "entidade": "Anúncio de procedimento  n.º 16548/2026  -  Diário da República n.º 123/2026, Série II de 2026-06-29",
    "link": "https://diariodarepublica.pt/dr/detalhe/anuncio-procedimento/16548-2026-1139905320"
  },
  {
    "numero_procedimento": "N/A",
    "entidade": "Anúncio de procedimento  n.º 16550/2026  -  Diário da República n.º 123/2026, Série II de 2026-06-29",
    "link": "https://diariodarepublica.pt/dr/detalhe/anuncio-procedimento/16550-2026-1139905321"
  },
  {
    "numero_procedimento": "N/A",
    "entidade": "Anúncio de procedimento  n.º 16552/2026  -  Diário da República n.º 123/2026, Série II de 2026-06-29",
    "link": "https://diariodarepublica.pt/dr/detalhe/anuncio-procedimento/16552-2026-1139905322"
  },
  {
    "numero_procedimento": "N/A",
    "entidade": "Anúncio de procedimento  n.º 16554/2026  -  Diário da República n.º 123/2026, Série II de 2026-06-29",
    "link": "https://diariodarepublica.pt/dr/detalhe/anuncio-procedimento/16554-2026-1139905323"
  },
  {
    "numero_procedimento": "N/A",
    "entidade": "Anúncio de procedimento  n.º 16556/2026  -  Diário da República n.º 123/2026, Série II de 2026-06-29",
    "link": "https://diariodarepublica.pt/dr/detalhe/anuncio-procedimento/16556-2026-1139905324"
  },
  {
    "numero_procedimento": "N/A",
    "entidade": "Anúncio de procedimento  n.º 16558/2026  -  Diário da República n.º 123/2026, Série II de 2026-06-29",
    "link": "https://diariodarepublica.pt/dr/detalhe/anuncio-procedimento/16558-2026-1139905325"
  },
  {
    "numero_procedimento": "N/A",
    "entidade": "Anúncio de procedimento  n.º 16560/2026  -  Diário da República n.º 123/2026, Série II de 2026-06-29",
    "link": "https://diariodarepublica.pt/dr/detalhe/anuncio-procedimento/16560-2026-1139905326"
  },
  {
    "numero_procedimento": "N/A",
    "entidade": "Anúncio de procedimento  n.º 16562/2026  -  Diário da República n.º 123/2026, Série II de 2026-06-29",
    "link": "https://diariodarepublica.pt/dr/detalhe/anuncio-procedimento/16562-2026-1139905327"
  },
  {
    "numero_procedimento": "N/A",
    "entidade": "Anúncio de procedimento  n.º 16564/2026  -  Diário da República n.º 123/2026, Série II de 2026-06-29",
    "link": "https://diariodarepublica.pt/dr/detalhe/anuncio-procedimento/16564-2026-1139905328"
  },
  {
    "numero_procedimento": "N/A",
    "entidade": "Anúncio de procedimento  n.º 16566/2026  -  Diário da República n.º 123/2026, Série II de 2026-06-29",
    "link": "https://diariodarepublica.pt/dr/detalhe/anuncio-procedimento/16566-2026-1139905329"
  },
  {
    "numero_procedimento": "N/A",
    "entidade": "Anúncio de procedimento  n.º 16567/2026  -  Diário da República n.º 123/2026, Série II de 2026-06-29",
    "link": "https://diariodarepublica.pt/dr/detalhe/anuncio-procedimento/16567-2026-1139905330"
  },
  {
    "numero_procedimento": "N/A",
    "entidade": "Anúncio de procedimento  n.º 16571/2026  -  Diário da República n.º 123/2026, Série II de 2026-06-29",
    "link": "https://diariodarepublica.pt/dr/detalhe/anuncio-procedimento/16571-2026-1139905331"
  },
  {
    "numero_procedimento": "N/A",
    "entidade": "Anúncio de procedimento  n.º 16572/2026  -  Diário da República n.º 123/2026, Série II de 2026-06-29",
    "link": "https://diariodarepublica.pt/dr/detalhe/anuncio-procedimento/16572-2026-1139905332"
  },
  {
    "numero_procedimento": "N/A",
    "entidade": "Anúncio de procedimento  n.º 16575/2026  -  Diário da República n.º 123/2026, Série II de 2026-06-29",
    "link": "https://diariodarepublica.pt/dr/detalhe/anuncio-procedimento/16575-2026-1139905333"
  },
  {
    "numero_procedimento": "N/A",
    "entidade": "Anúncio de procedimento  n.º 16579/2026  -  Diário da República n.º 123/2026, Série II de 2026-06-29",
    "link": "https://diariodarepublica.pt/dr/detalhe/anuncio-procedimento/16579-2026-1139905334"
  },
  {
    "numero_procedimento": "N/A",
    "entidade": "Anúncio de procedimento  n.º 16583/2026  -  Diário da República n.º 123/2026, Série II de 2026-06-29",
    "link": "https://diariodarepublica.pt/dr/detalhe/anuncio-procedimento/16583-2026-1139905335"
  },
  {
    "numero_procedimento": "N/A",
    "entidade": "Anúncio de procedimento  n.º 16586/2026  -  Diário da República n.º 123/2026, Série II de 2026-06-29",
    "link": "https://diariodarepublica.pt/dr/detalhe/anuncio-procedimento/16586-2026-1139905336"
  },
  {
    "numero_procedimento": "N/A",
    "entidade": "Anúncio de procedimento  n.º 16588/2026  -  Diário da República n.º 123/2026, Série II de 2026-06-29",
    "link": "https://diariodarepublica.pt/dr/detalhe/anuncio-procedimento/16588-2026-1139905337"
  },
  {
    "numero_procedimento": "N/A",
    "entidade": "Anúncio de procedimento  n.º 16591/2026  -  Diário da República n.º 123/2026, Série II de 2026-06-29",
    "link": "https://diariodarepublica.pt/dr/detalhe/anuncio-procedimento/16591-2026-1139905338"
  },
  {
    "numero_procedimento": "N/A",
    "entidade": "Anúncio de procedimento  n.º 16592/2026  -  Diário da República n.º 123/2026, Série II de 2026-06-29",
    "link": "https://diariodarepublica.pt/dr/detalhe/anuncio-procedimento/16592-2026-1139905339"
  },
  {
    "numero_procedimento": "N/A",
    "entidade": "Anúncio de procedimento  n.º 16594/2026  -  Diário da República n.º 123/2026, Série II de 2026-06-29",
    "link": "https://diariodarepublica.pt/dr/detalhe/anuncio-procedimento/16594-2026-1139905340"
  },
  {
    "numero_procedimento": "N/A",
    "entidade": "Anúncio de procedimento  n.º 16596/2026  -  Diário da República n.º 123/2026, Série II de 2026-06-29",
    "link": "https://diariodarepublica.pt/dr/detalhe/anuncio-procedimento/16596-2026-1139905341"
  },
  {
    "numero_procedimento": "N/A",
    "entidade": "Anúncio de procedimento  n.º 16598/2026  -  Diário da República n.º 123/2026, Série II de 2026-06-29",
    "link": "https://diariodarepublica.pt/dr/detalhe/anuncio-procedimento/16598-2026-1139905345"
  },
  {
    "numero_procedimento": "N/A",
    "entidade": "Anúncio de procedimento  n.º 16600/2026  -  Diário da República n.º 123/2026, Série II de 2026-06-29",
    "link": "https://diariodarepublica.pt/dr/detalhe/anuncio-procedimento/16600-2026-1139905346"
  },
  {
    "numero_procedimento": "N/A",
    "entidade": "Anúncio de procedimento  n.º 16604/2026  -  Diário da República n.º 123/2026, Série II de 2026-06-29",
    "link": "https://diariodarepublica.pt/dr/detalhe/anuncio-procedimento/16604-2026-1139905347"
  },
  {
    "numero_procedimento": "N/A",
    "entidade": "Anúncio de procedimento  n.º 16605/2026  -  Diário da República n.º 123/2026, Série II de 2026-06-29",
    "link": "https://diariodarepublica.pt/dr/detalhe/anuncio-procedimento/16605-2026-1139905348"
  },
  {
    "numero_procedimento": "N/A",
    "entidade": "Anúncio de procedimento  n.º 16606/2026  -  Diário da República n.º 123/2026, Série II de 2026-06-29",
    "link": "https://diariodarepublica.pt/dr/detalhe/anuncio-procedimento/16606-2026-1139905349"
  },
  {
    "numero_procedimento": "N/A",
    "entidade": "Anúncio de procedimento  n.º 16607/2026  -  Diário da República n.º 123/2026, Série II de 2026-06-29",
    "link": "https://diariodarepublica.pt/dr/detalhe/anuncio-procedimento/16607-2026-1139905350"
  },
  {
    "numero_procedimento": "N/A",
    "entidade": "Anúncio de procedimento  n.º 16610/2026  -  Diário da República n.º 123/2026, Série II de 2026-06-29",
    "link": "https://diariodarepublica.pt/dr/detalhe/anuncio-procedimento/16610-2026-1139905351"
  },
  {
    "numero_procedimento": "N/A",
    "entidade": "Anúncio de procedimento  n.º 16611/2026  -  Diário da República n.º 123/2026, Série II de 2026-06-29",
    "link": "https://diariodarepublica.pt/dr/detalhe/anuncio-procedimento/16611-2026-1139905352"
  },
  {
    "numero_procedimento": "N/A",
    "entidade": "Anúncio de procedimento  n.º 16612/2026  -  Diário da República n.º 123/2026, Série II de 2026-06-29",
    "link": "https://diariodarepublica.pt/dr/detalhe/anuncio-procedimento/16612-2026-1139905353"
  },
  {
    "numero_procedimento": "N/A",
    "entidade": "Anúncio de procedimento  n.º 16519/2026  -  Diário da República n.º 123/2026, Série II de 2026-06-29",
    "link": "https://diariodarepublica.pt/dr/detalhe/anuncio-procedimento/16519-2026-1139971702"
  },
  {
    "numero_procedimento": "N/A",
    "entidade": "Anúncio de procedimento  n.º 16522/2026  -  Diário da República n.º 123/2026, Série II de 2026-06-29",
    "link": "https://diariodarepublica.pt/dr/detalhe/anuncio-procedimento/16522-2026-1139971703"
  },
  {
    "numero_procedimento": "N/A",
    "entidade": "Anúncio de procedimento  n.º 16523/2026  -  Diário da República n.º 123/2026, Série II de 2026-06-29",
    "link": "https://diariodarepublica.pt/dr/detalhe/anuncio-procedimento/16523-2026-1139971704"
  },
  {
    "numero_procedimento": "N/A",
    "entidade": "Anúncio de procedimento  n.º 16524/2026  -  Diário da República n.º 123/2026, Série II de 2026-06-29",
    "link": "https://diariodarepublica.pt/dr/detalhe/anuncio-procedimento/16524-2026-1139971705"
  },
  {
    "numero_procedimento": "N/A",
    "entidade": "Anúncio de procedimento  n.º 16527/2026  -  Diário da República n.º 123/2026, Série II de 2026-06-29",
    "link": "https://diariodarepublica.pt/dr/detalhe/anuncio-procedimento/16527-2026-1139971706"
  },
  {
    "numero_procedimento": "N/A",
    "entidade": "Anúncio de procedimento  n.º 16529/2026  -  Diário da República n.º 123/2026, Série II de 2026-06-29",
    "link": "https://diariodarepublica.pt/dr/detalhe/anuncio-procedimento/16529-2026-1139971707"
  },
  {
    "numero_procedimento": "N/A",
    "entidade": "Anúncio de procedimento  n.º 16531/2026  -  Diário da República n.º 123/2026, Série II de 2026-06-29",
    "link": "https://diariodarepublica.pt/dr/detalhe/anuncio-procedimento/16531-2026-1139971708"
  },
  {
    "numero_procedimento": "N/A",
    "entidade": "Anúncio de procedimento  n.º 16533/2026  -  Diário da República n.º 123/2026, Série II de 2026-06-29",
    "link": "https://diariodarepublica.pt/dr/detalhe/anuncio-procedimento/16533-2026-1139971709"
  },
  {
    "numero_procedimento": "N/A",
    "entidade": "Anúncio de procedimento  n.º 16535/2026  -  Diário da República n.º 123/2026, Série II de 2026-06-29",
    "link": "https://diariodarepublica.pt/dr/detalhe/anuncio-procedimento/16535-2026-1139971710"
  },
  {
    "numero_procedimento": "N/A",
    "entidade": "Anúncio de procedimento  n.º 16537/2026  -  Diário da República n.º 123/2026, Série II de 2026-06-29",
    "link": "https://diariodarepublica.pt/dr/detalhe/anuncio-procedimento/16537-2026-1139971711"
  },
  {
    "numero_procedimento": "N/A",
    "entidade": "Anúncio de procedimento  n.º 16539/2026  -  Diário da República n.º 123/2026, Série II de 2026-06-29",
    "link": "https://diariodarepublica.pt/dr/detalhe/anuncio-procedimento/16539-2026-1139971712"
  },
  {
    "numero_procedimento": "N/A",
    "entidade": "Anúncio de procedimento  n.º 16541/2026  -  Diário da República n.º 123/2026, Série II de 2026-06-29",
    "link": "https://diariodarepublica.pt/dr/detalhe/anuncio-procedimento/16541-2026-1139971713"
  },
  {
    "numero_procedimento": "N/A",
    "entidade": "Anúncio de procedimento  n.º 16543/2026  -  Diário da República n.º 123/2026, Série II de 2026-06-29",
    "link": "https://diariodarepublica.pt/dr/detalhe/anuncio-procedimento/16543-2026-1139971714"
  },
  {
    "numero_procedimento": "N/A",
    "entidade": "Anúncio de procedimento  n.º 16545/2026  -  Diário da República n.º 123/2026, Série II de 2026-06-29",
    "link": "https://diariodarepublica.pt/dr/detalhe/anuncio-procedimento/16545-2026-1139971715"
  },
  {
    "numero_procedimento": "N/A",
    "entidade": "Anúncio de procedimento  n.º 16547/2026  -  Diário da República n.º 123/2026, Série II de 2026-06-29",
    "link": "https://diariodarepublica.pt/dr/detalhe/anuncio-procedimento/16547-2026-1139971716"
  },
  {
    "numero_procedimento": "N/A",
    "entidade": "Anúncio de procedimento  n.º 16549/2026  -  Diário da República n.º 123/2026, Série II de 2026-06-29",
    "link": "https://diariodarepublica.pt/dr/detalhe/anuncio-procedimento/16549-2026-1139971717"
  },
  {
    "numero_procedimento": "N/A",
    "entidade": "Anúncio de procedimento  n.º 16551/2026  -  Diário da República n.º 123/2026, Série II de 2026-06-29",
    "link": "https://diariodarepublica.pt/dr/detalhe/anuncio-procedimento/16551-2026-1139971718"
  },
  {
    "numero_procedimento": "N/A",
    "entidade": "Anúncio de procedimento  n.º 16553/2026  -  Diário da República n.º 123/2026, Série II de 2026-06-29",
    "link": "https://diariodarepublica.pt/dr/detalhe/anuncio-procedimento/16553-2026-1139971719"
  },
  {
    "numero_procedimento": "N/A",
    "entidade": "Anúncio de procedimento  n.º 16555/2026  -  Diário da República n.º 123/2026, Série II de 2026-06-29",
    "link": "https://diariodarepublica.pt/dr/detalhe/anuncio-procedimento/16555-2026-1139971720"
  },
  {
    "numero_procedimento": "N/A",
    "entidade": "Anúncio de procedimento  n.º 16557/2026  -  Diário da República n.º 123/2026, Série II de 2026-06-29",
    "link": "https://diariodarepublica.pt/dr/detalhe/anuncio-procedimento/16557-2026-1139971721"
  },
  {
    "numero_procedimento": "N/A",
    "entidade": "Anúncio de procedimento  n.º 16559/2026  -  Diário da República n.º 123/2026, Série II de 2026-06-29",
    "link": "https://diariodarepublica.pt/dr/detalhe/anuncio-procedimento/16559-2026-1139971722"
  },
  {
    "numero_procedimento": "N/A",
    "entidade": "Anúncio de procedimento  n.º 16561/2026  -  Diário da República n.º 123/2026, Série II de 2026-06-29",
    "link": "https://diariodarepublica.pt/dr/detalhe/anuncio-procedimento/16561-2026-1139971723"
  },
  {
    "numero_procedimento": "N/A",
    "entidade": "Anúncio de procedimento  n.º 16563/2026  -  Diário da República n.º 123/2026, Série II de 2026-06-29",
    "link": "https://diariodarepublica.pt/dr/detalhe/anuncio-procedimento/16563-2026-1139971724"
  },
  {
    "numero_procedimento": "N/A",
    "entidade": "Anúncio de procedimento  n.º 16565/2026  -  Diário da República n.º 123/2026, Série II de 2026-06-29",
    "link": "https://diariodarepublica.pt/dr/detalhe/anuncio-procedimento/16565-2026-1139971725"
  },
  {
    "numero_procedimento": "N/A",
    "entidade": "Anúncio de procedimento  n.º 16568/2026  -  Diário da República n.º 123/2026, Série II de 2026-06-29",
    "link": "https://diariodarepublica.pt/dr/detalhe/anuncio-procedimento/16568-2026-1139971726"
  },
  {
    "numero_procedimento": "N/A",
    "entidade": "Anúncio de procedimento  n.º 16573/2026  -  Diário da República n.º 123/2026, Série II de 2026-06-29",
    "link": "https://diariodarepublica.pt/dr/detalhe/anuncio-procedimento/16573-2026-1139971730"
  },
  {
    "numero_procedimento": "N/A",
    "entidade": "Anúncio de procedimento  n.º 16574/2026  -  Diário da República n.º 123/2026, Série II de 2026-06-29",
    "link": "https://diariodarepublica.pt/dr/detalhe/anuncio-procedimento/16574-2026-1139971731"
  },
  {
    "numero_procedimento": "N/A",
    "entidade": "Anúncio de procedimento  n.º 16576/2026  -  Diário da República n.º 123/2026, Série II de 2026-06-29",
    "link": "https://diariodarepublica.pt/dr/detalhe/anuncio-procedimento/16576-2026-1139971732"
  },
  {
    "numero_procedimento": "N/A",
    "entidade": "Anúncio de procedimento  n.º 16577/2026  -  Diário da República n.º 123/2026, Série II de 2026-06-29",
    "link": "https://diariodarepublica.pt/dr/detalhe/anuncio-procedimento/16577-2026-1139971733"
  },
  {
    "numero_procedimento": "N/A",
    "entidade": "Anúncio de procedimento  n.º 16578/2026  -  Diário da República n.º 123/2026, Série II de 2026-06-29",
    "link": "https://diariodarepublica.pt/dr/detalhe/anuncio-procedimento/16578-2026-1139971734"
  },
  {
    "numero_procedimento": "N/A",
    "entidade": "Anúncio de procedimento  n.º 16580/2026  -  Diário da República n.º 123/2026, Série II de 2026-06-29",
    "link": "https://diariodarepublica.pt/dr/detalhe/anuncio-procedimento/16580-2026-1139971735"
  },
  {
    "numero_procedimento": "N/A",
    "entidade": "Anúncio de procedimento  n.º 16581/2026  -  Diário da República n.º 123/2026, Série II de 2026-06-29",
    "link": "https://diariodarepublica.pt/dr/detalhe/anuncio-procedimento/16581-2026-1139971736"
  },
  {
    "numero_procedimento": "N/A",
    "entidade": "Anúncio de procedimento  n.º 16582/2026  -  Diário da República n.º 123/2026, Série II de 2026-06-29",
    "link": "https://diariodarepublica.pt/dr/detalhe/anuncio-procedimento/16582-2026-1139971737"
  },
  {
    "numero_procedimento": "N/A",
    "entidade": "Anúncio de procedimento  n.º 16584/2026  -  Diário da República n.º 123/2026, Série II de 2026-06-29",
    "link": "https://diariodarepublica.pt/dr/detalhe/anuncio-procedimento/16584-2026-1139971741"
  },
  {
    "numero_procedimento": "N/A",
    "entidade": "Anúncio de procedimento  n.º 16585/2026  -  Diário da República n.º 123/2026, Série II de 2026-06-29",
    "link": "https://diariodarepublica.pt/dr/detalhe/anuncio-procedimento/16585-2026-1139971742"
  },
  {
    "numero_procedimento": "N/A",
    "entidade": "Anúncio de procedimento  n.º 16587/2026  -  Diário da República n.º 123/2026, Série II de 2026-06-29",
    "link": "https://diariodarepublica.pt/dr/detalhe/anuncio-procedimento/16587-2026-1139971743"
  },
  {
    "numero_procedimento": "N/A",
    "entidade": "Anúncio de procedimento  n.º 16589/2026  -  Diário da República n.º 123/2026, Série II de 2026-06-29",
    "link": "https://diariodarepublica.pt/dr/detalhe/anuncio-procedimento/16589-2026-1139971744"
  },
  {
    "numero_procedimento": "N/A",
    "entidade": "Anúncio de procedimento  n.º 16590/2026  -  Diário da República n.º 123/2026, Série II de 2026-06-29",
    "link": "https://diariodarepublica.pt/dr/detalhe/anuncio-procedimento/16590-2026-1139971746"
  },
  {
    "numero_procedimento": "N/A",
    "entidade": "Anúncio de procedimento  n.º 16593/2026  -  Diário da República n.º 123/2026, Série II de 2026-06-29",
    "link": "https://diariodarepublica.pt/dr/detalhe/anuncio-procedimento/16593-2026-1139971747"
  },
  {
    "numero_procedimento": "N/A",
    "entidade": "Anúncio de procedimento  n.º 16595/2026  -  Diário da República n.º 123/2026, Série II de 2026-06-29",
    "link": "https://diariodarepublica.pt/dr/detalhe/anuncio-procedimento/16595-2026-1139971748"
  },
  {
    "numero_procedimento": "N/A",
    "entidade": "Anúncio de procedimento  n.º 16597/2026  -  Diário da República n.º 123/2026, Série II de 2026-06-29",
    "link": "https://diariodarepublica.pt/dr/detalhe/anuncio-procedimento/16597-2026-1139971750"
  },
  {
    "numero_procedimento": "N/A",
    "entidade": "Anúncio de procedimento  n.º 16599/2026  -  Diário da República n.º 123/2026, Série II de 2026-06-29",
    "link": "https://diariodarepublica.pt/dr/detalhe/anuncio-procedimento/16599-2026-1139971751"
  },
  {
    "numero_procedimento": "N/A",
    "entidade": "Anúncio de procedimento  n.º 16601/2026  -  Diário da República n.º 123/2026, Série II de 2026-06-29",
    "link": "https://diariodarepublica.pt/dr/detalhe/anuncio-procedimento/16601-2026-1139971752"
  },
  {
    "numero_procedimento": "N/A",
    "entidade": "Anúncio de procedimento  n.º 16602/2026  -  Diário da República n.º 123/2026, Série II de 2026-06-29",
    "link": "https://diariodarepublica.pt/dr/detalhe/anuncio-procedimento/16602-2026-1139971753"
  },
  {
    "numero_procedimento": "N/A",
    "entidade": "Anúncio de procedimento  n.º 16603/2026  -  Diário da República n.º 123/2026, Série II de 2026-06-29",
    "link": "https://diariodarepublica.pt/dr/detalhe/anuncio-procedimento/16603-2026-1139971757"
  },
  {
    "numero_procedimento": "N/A",
    "entidade": "Anúncio de procedimento  n.º 16608/2026  -  Diário da República n.º 123/2026, Série II de 2026-06-29",
    "link": "https://diariodarepublica.pt/dr/detalhe/anuncio-procedimento/16608-2026-1139971759"
  },
  {
    "numero_procedimento": "N/A",
    "entidade": "Anúncio de procedimento  n.º 16609/2026  -  Diário da República n.º 123/2026, Série II de 2026-06-29",
    "link": "https://diariodarepublica.pt/dr/detalhe/anuncio-procedimento/16609-2026-1139971760"
  },
  {
    "numero_procedimento": "N/A",
    "entidade": "Anúncio de procedimento  n.º 16616/2026  -  Diário da República n.º 123/2026, Série II de 2026-06-29",
    "link": "https://diariodarepublica.pt/dr/detalhe/anuncio-procedimento/16616-2026-1139971762"
  },
  {
    "numero_procedimento": "N/A",
    "entidade": "Anúncio de procedimento  n.º 16620/2026  -  Diário da República n.º 123/2026, Série II de 2026-06-29",
    "link": "https://diariodarepublica.pt/dr/detalhe/anuncio-procedimento/16620-2026-1139971763"
  },
  {
    "numero_procedimento": "N/A",
    "entidade": "Anúncio de procedimento  n.º 16622/2026  -  Diário da República n.º 123/2026, Série II de 2026-06-29",
    "link": "https://diariodarepublica.pt/dr/detalhe/anuncio-procedimento/16622-2026-1139971764"
  },
  {
    "numero_procedimento": "N/A",
    "entidade": "Anúncio de procedimento  n.º 16569/2026  -  Diário da República n.º 123/2026, Série II de 2026-06-29",
    "link": "https://diariodarepublica.pt/dr/detalhe/anuncio-procedimento/16569-2026-1139971765"
  },
  {
    "numero_procedimento": "N/A",
    "entidade": "Anúncio de procedimento  n.º 16624/2026  -  Diário da República n.º 123/2026, Série II de 2026-06-29",
    "link": "https://diariodarepublica.pt/dr/detalhe/anuncio-procedimento/16624-2026-1139971766"
  },
  {
    "numero_procedimento": "N/A",
    "entidade": "Anúncio de procedimento  n.º 16625/2026  -  Diário da República n.º 123/2026, Série II de 2026-06-29",
    "link": "https://diariodarepublica.pt/dr/detalhe/anuncio-procedimento/16625-2026-1139971767"
  },
  {
    "numero_procedimento": "N/A",
    "entidade": "Anúncio de procedimento  n.º 16627/2026  -  Diário da República n.º 123/2026, Série II de 2026-06-29",
    "link": "https://diariodarepublica.pt/dr/detalhe/anuncio-procedimento/16627-2026-1139971768"
  },
  {
    "numero_procedimento": "N/A",
    "entidade": "Anúncio de procedimento  n.º 16629/2026  -  Diário da República n.º 123/2026, Série II de 2026-06-29",
    "link": "https://diariodarepublica.pt/dr/detalhe/anuncio-procedimento/16629-2026-1139971769"
  },
  {
    "numero_procedimento": "N/A",
    "entidade": "Anúncio de procedimento  n.º 16613/2026  -  Diário da República n.º 123/2026, Série II de 2026-06-29",
    "link": "https://diariodarepublica.pt/dr/detalhe/anuncio-procedimento/16613-2026-1140235953"
  },
  {
    "numero_procedimento": "N/A",
    "entidade": "Anúncio de procedimento  n.º 16614/2026  -  Diário da República n.º 123/2026, Série II de 2026-06-29",
    "link": "https://diariodarepublica.pt/dr/detalhe/anuncio-procedimento/16614-2026-1140235954"
  },
  {
    "numero_procedimento": "N/A",
    "entidade": "Anúncio de procedimento  n.º 16615/2026  -  Diário da República n.º 123/2026, Série II de 2026-06-29",
    "link": "https://diariodarepublica.pt/dr/detalhe/anuncio-procedimento/16615-2026-1140235955"
  },
  {
    "numero_procedimento": "N/A",
    "entidade": "Anúncio de procedimento  n.º 16617/2026  -  Diário da República n.º 123/2026, Série II de 2026-06-29",
    "link": "https://diariodarepublica.pt/dr/detalhe/anuncio-procedimento/16617-2026-1140235956"
  },
  {
    "numero_procedimento": "N/A",
    "entidade": "Anúncio de procedimento  n.º 16618/2026  -  Diário da República n.º 123/2026, Série II de 2026-06-29",
    "link": "https://diariodarepublica.pt/dr/detalhe/anuncio-procedimento/16618-2026-1140235957"
  },
  {
    "numero_procedimento": "N/A",
    "entidade": "Anúncio de procedimento  n.º 16619/2026  -  Diário da República n.º 123/2026, Série II de 2026-06-29",
    "link": "https://diariodarepublica.pt/dr/detalhe/anuncio-procedimento/16619-2026-1140235958"
  },
  {
    "numero_procedimento": "N/A",
    "entidade": "Anúncio de procedimento  n.º 16621/2026  -  Diário da República n.º 123/2026, Série II de 2026-06-29",
    "link": "https://diariodarepublica.pt/dr/detalhe/anuncio-procedimento/16621-2026-1140235959"
  },
  {
    "numero_procedimento": "N/A",
    "entidade": "Anúncio de procedimento  n.º 16623/2026  -  Diário da República n.º 123/2026, Série II de 2026-06-29",
    "link": "https://diariodarepublica.pt/dr/detalhe/anuncio-procedimento/16623-2026-1140235960"
  },
  {
    "numero_procedimento": "N/A",
    "entidade": "Anúncio de procedimento  n.º 16626/2026  -  Diário da República n.º 123/2026, Série II de 2026-06-29",
    "link": "https://diariodarepublica.pt/dr/detalhe/anuncio-procedimento/16626-2026-1140235961"
  },
  {
    "numero_procedimento": "N/A",
    "entidade": "Anúncio de procedimento  n.º 16628/2026  -  Diário da República n.º 123/2026, Série II de 2026-06-29",
    "link": "https://diariodarepublica.pt/dr/detalhe/anuncio-procedimento/16628-2026-1140235962"
  },
  {
    "numero_procedimento": "N/A",
    "entidade": "Anúncio de procedimento  n.º 16630/2026  -  Diário da República n.º 123/2026, Série II de 2026-06-29",
    "link": "https://diariodarepublica.pt/dr/detalhe/anuncio-procedimento/16630-2026-1140235963"
  },
  {
    "numero_procedimento": "N/A",
    "entidade": "Anúncio de procedimento  n.º 16632/2026  -  Diário da República n.º 123/2026, Série II de 2026-06-29",
    "link": "https://diariodarepublica.pt/dr/detalhe/anuncio-procedimento/16632-2026-1140235964"
  },
  {
    "numero_procedimento": "N/A",
    "entidade": "Anúncio de procedimento  n.º 16633/2026  -  Diário da República n.º 123/2026, Série II de 2026-06-29",
    "link": "https://diariodarepublica.pt/dr/detalhe/anuncio-procedimento/16633-2026-1140235965"
  },
  {
    "numero_procedimento": "N/A",
    "entidade": "Anúncio de procedimento  n.º 16634/2026  -  Diário da República n.º 123/2026, Série II de 2026-06-29",
    "link": "https://diariodarepublica.pt/dr/detalhe/anuncio-procedimento/16634-2026-1140235966"
  },
  {
    "numero_procedimento": "N/A",
    "entidade": "Anúncio de procedimento  n.º 16635/2026  -  Diário da República n.º 123/2026, Série II de 2026-06-29",
    "link": "https://diariodarepublica.pt/dr/detalhe/anuncio-procedimento/16635-2026-1140235967"
  },
  {
    "numero_procedimento": "N/A",
    "entidade": "Anúncio de procedimento  n.º 16636/2026  -  Diário da República n.º 123/2026, Série II de 2026-06-29",
    "link": "https://diariodarepublica.pt/dr/detalhe/anuncio-procedimento/16636-2026-1140235968"
  },
  {
    "numero_procedimento": "N/A",
    "entidade": "Anúncio de procedimento  n.º 16637/2026  -  Diário da República n.º 123/2026, Série II de 2026-06-29",
    "link": "https://diariodarepublica.pt/dr/detalhe/anuncio-procedimento/16637-2026-1140235969"
  },
  {
    "numero_procedimento": "N/A",
    "entidade": "Anúncio de procedimento  n.º 16638/2026  -  Diário da República n.º 123/2026, Série II de 2026-06-29",
    "link": "https://diariodarepublica.pt/dr/detalhe/anuncio-procedimento/16638-2026-1140235970"
  },
  {
    "numero_procedimento": "N/A",
    "entidade": "Anúncio de procedimento  n.º 16642/2026  -  Diário da República n.º 123/2026, Série II de 2026-06-29",
    "link": "https://diariodarepublica.pt/dr/detalhe/anuncio-procedimento/16642-2026-1140235971"
  },
  {
    "numero_procedimento": "N/A",
    "entidade": "Anúncio de procedimento  n.º 16643/2026  -  Diário da República n.º 123/2026, Série II de 2026-06-29",
    "link": "https://diariodarepublica.pt/dr/detalhe/anuncio-procedimento/16643-2026-1140235973"
  },
  {
    "numero_procedimento": "N/A",
    "entidade": "Anúncio de procedimento  n.º 16644/2026  -  Diário da República n.º 123/2026, Série II de 2026-06-29",
    "link": "https://diariodarepublica.pt/dr/detalhe/anuncio-procedimento/16644-2026-1140235974"
  },
  {
    "numero_procedimento": "N/A",
    "entidade": "Anúncio de procedimento  n.º 16631/2026  -  Diário da República n.º 123/2026, Série II de 2026-06-29",
    "link": "https://diariodarepublica.pt/dr/detalhe/anuncio-procedimento/16631-2026-1140260278"
  },
  {
    "numero_procedimento": "N/A",
    "entidade": "Anúncio de procedimento  n.º 16570/2026  -  Diário da República n.º 123/2026, Série II de 2026-06-29",
    "link": "https://diariodarepublica.pt/dr/detalhe/anuncio-procedimento/16570-2026-1140260282"
  },
  {
    "numero_procedimento": "N/A",
    "entidade": "Anúncio de procedimento  n.º 16639/2026  -  Diário da República n.º 123/2026, Série II de 2026-06-29",
    "link": "https://diariodarepublica.pt/dr/detalhe/anuncio-procedimento/16639-2026-1140260283"
  },
  {
    "numero_procedimento": "N/A",
    "entidade": "Anúncio de procedimento  n.º 16640/2026  -  Diário da República n.º 123/2026, Série II de 2026-06-29",
    "link": "https://diariodarepublica.pt/dr/detalhe/anuncio-procedimento/16640-2026-1140260287"
  },
  {
    "numero_procedimento": "N/A",
    "entidade": "Anúncio de procedimento  n.º 16641/2026  -  Diário da República n.º 123/2026, Série II de 2026-06-29",
    "link": "https://diariodarepublica.pt/dr/detalhe/anuncio-procedimento/16641-2026-1140260288"
  }
]